[{"id":0,"zemepisnaSirka":50.08011568015412,"zemepisnaDelka":14.429806835937503,"pocatecniCas":{"date":{"year":2022,"month":1,"day":20},"time":{"hour":12,"minute":0,"second":0,"nano":0}},"konecnyCas":{"date":{"year":2022,"month":1,"day":21},"time":{"hour":12,"minute":0,"second":0,"nano":0}},"dest":false,"formalnostObleceni":["HODNE","STREDNE","MALO"]},{"id":1,"zemepisnaSirka":50.08187817293684,"zemepisnaDelka":14.531430371093753,"pocatecniCas":{"date":{"year":2022,"month":1,"day":20},"time":{"hour":12,"minute":0,"second":0,"nano":0}},"konecnyCas":{"date":{"year":2022,"month":1,"day":21},"time":{"hour":12,"minute":0,"second":0,"nano":0}},"dest":false,"formalnostObleceni":["STREDNE","MALO"]},{"id":2,"zemepisnaSirka":50.09773769214589,"zemepisnaDelka":14.389981396484378,"pocatecniCas":{"date":{"year":2022,"month":1,"day":20},"time":{"hour":20,"minute":0,"second":0,"nano":0}},"konecnyCas":{"date":{"year":2022,"month":1,"day":21},"time":{"hour":12,"minute":0,"second":0,"nano":0}},"dest":false,"formalnostObleceni":["HODNE","STREDNE","MALO"]},{"id":3,"zemepisnaSirka":50.14000408723536,"zemepisnaDelka":14.270505078125003,"pocatecniCas":{"date":{"year":2022,"month":1,"day":19},"time":{"hour":12,"minute":0,"second":0,"nano":0}},"konecnyCas":{"date":{"year":2022,"month":1,"day":20},"time":{"hour":12,"minute":0,"second":0,"nano":0}},"dest":false,"formalnostObleceni":["STREDNE"]}]